pypsh-0.7.2.dist-info/RECORD
pypsh-0.7.2.dist-info/top_level.txt
pypsh-0.7.2.dist-info/METADATA
pypsh-0.7.2.dist-info/entry_points.txt
pypsh-0.7.2.dist-info/DESCRIPTION.rst
pypsh-0.7.2.dist-info/WHEEL
pypsh-0.7.2.dist-info/metadata.json
pypsh/__init__.py
pypsh/main.py
