Metadata-Version: 2.0
Name: pypsh
Version: 0.7.2
Summary: pypsh - cli for parallel ssh command execution on all known hosts that match a
Requires-Dist: paramiko
Requires-Dist: termcolor
